md/__init__.py
md/auction.py
md/auction_csv.py
md/auction_json.py
md/auction_txt.py
md/lindsay2018.py
marketdesign-0.0.1a1.dist-info/METADATA
marketdesign-0.0.1a1.dist-info/WHEEL
marketdesign-0.0.1a1.dist-info/licenses/LICENSE
marketdesign-0.0.1a1.dist-info/RECORD
