Metadata-Version: 2.1
Name: marketdesign
Version: 0.0.1a1
Summary: This project is a python implementation of the market mechanism described in the paper 'Shapley value based pricing for auctions and exchanges' (Lindsay 2018).
Project-URL: Homepage, https://github.com/luke777/marketdesign
Author-email: Luke Lindsay <l.lindsay@exeter.ac.uk>
License-File: LICENSE
Classifier: License :: OSI Approved :: MIT License
Classifier: Operating System :: OS Independent
Classifier: Programming Language :: Python :: 3
Requires-Python: >=3.7
Requires-Dist: chardet~=4.0.0
Requires-Dist: mip==1.14.0
Requires-Dist: tabulate~=0.8.9
